windowsregistry/__init__.py
windowsregistry/_backend.py
windowsregistry/_lowlevel.py
windowsregistry/_typings.py
windowsregistry/core.py
windowsregistry/errors.py
windowsregistry/models/__init__.py
windowsregistry/models/data.py
windowsregistry/models/enums.py
windowsregistry/py.typed
windowsregistry/regpath.py
windowsregistry/utils.py
windowsregistry-0.1.3.dist-info/LICENSE
windowsregistry-0.1.3.dist-info/METADATA
windowsregistry-0.1.3.dist-info/WHEEL
windowsregistry-0.1.3.dist-info/RECORD
