Metadata-Version: 2.1
Name: windowsregistry
Version: 0.1.3
Summary: Windows Registry Editor with Pythonic interface
Home-page: https://github.com/DinhHuy2010/windowsregistry.py
License: MIT
Author: DinhHuy2010
Author-email: huy04052010@outlook.com
Requires-Python: >=3.10,<4.0
Classifier: License :: OSI Approved :: MIT License
Classifier: Programming Language :: Python :: 3
Classifier: Programming Language :: Python :: 3.10
Classifier: Programming Language :: Python :: 3.11
Classifier: Programming Language :: Python :: 3.12
